print/__init__.py
print/print1.py
print/print2.py
print/print3.py
python_tools_test-0.0.1.dist-info/METADATA
python_tools_test-0.0.1.dist-info/WHEEL
python_tools_test-0.0.1.dist-info/top_level.txt
python_tools_test-0.0.1.dist-info/RECORD
