Metadata-Version: 2.1
Name: python-tools-test
Version: 0.0.1
Summary: test pypi
Home-page: https://github.com/1079893263
Author: wanggang
Author-email: 1079893263@qq.com
License: MIT
Platform: UNKNOWN
